{
    "1": [
        "sta1",
        "sta7",
        "sta12",
        "sta14",
        "sta25"
    ],
    "2": [
        "sta9",
        "sta13",
        "sta15",
        "sta18",
        "sta19",
        "sta21"
    ],
    "3": [
        "sta5",
        "sta6",
        "sta8",
        "sta10"
    ],
    "4": [
        "sta11",
        "sta17",
        "sta20",
        "sta24"
    ],
    "5": [
        "sta2",
        "sta3",
        "sta4",
        "sta16",
        "sta22",
        "sta23"
    ]
}